textflow_ai/__init__.py
textflow_ai/core.py
textflow_ai-0.1.1.dist-info/LICENSE
textflow_ai-0.1.1.dist-info/METADATA
textflow_ai-0.1.1.dist-info/WHEEL
textflow_ai-0.1.1.dist-info/top_level.txt
textflow_ai-0.1.1.dist-info/RECORD
