Metadata-Version: 2.1
Name: textflow-ai
Version: 0.1.1
Summary: A simple AI helper library
Home-page: UNKNOWN
Author: Athira Binu
Author-email: athirakbinu@gmail.com
License: MIT
Platform: UNKNOWN
License-File: LICENSE
